gosimplepack/__init__.py
gosimplepack/geometry.py
gosimplepack/hello.py
gosimplepack/operations.py
gosimplepack-0.5.0.dist-info/LICENSE
gosimplepack-0.5.0.dist-info/METADATA
gosimplepack-0.5.0.dist-info/WHEEL
gosimplepack-0.5.0.dist-info/top_level.txt
gosimplepack-0.5.0.dist-info/RECORD
