Metadata-Version: 2.1
Name: gosimplepack
Version: 0.5.0
Summary: Simple project that do basic math calculation.
Home-page: https://github.com/3ekodomo/gosimplepack
Author: 3ekodomo
Author-email: 3ekodomo@skiff.com
Keywords: simple,pythonpackage,example,3ekodomo
Classifier: Programming Language :: Python :: 3
Classifier: Programming Language :: Python :: 3.8
Classifier: Programming Language :: Python :: 3.9
Classifier: Programming Language :: Python :: 3.10
Classifier: Programming Language :: Python :: 3.11
Classifier: Operating System :: OS Independent
Classifier: License :: OSI Approved :: MIT License
Classifier: Natural Language :: English
Requires-Python: >=3.7
License-File: LICENSE
Requires-Dist: requests
